azure/__init__.py
azure/devops/__init__.py
azure/devops/_file_cache.py
azure/devops/_models.py
azure/devops/client.py
azure/devops/client_configuration.py
azure/devops/connection.py
azure/devops/credentials.py
azure/devops/exceptions.py
azure/devops/version.py
azure/devops/issue_tests/__init__.py
azure/devops/issue_tests/test_issue_268.py
azure/devops/released/__init__.py
azure/devops/released/client_factory.py
azure/devops/released/accounts/__init__.py
azure/devops/released/accounts/accounts_client.py
azure/devops/released/build/__init__.py
azure/devops/released/build/build_client.py
azure/devops/released/cloud_load_test/__init__.py
azure/devops/released/cloud_load_test/cloud_load_test_client.py
azure/devops/released/core/__init__.py
azure/devops/released/core/core_client.py
azure/devops/released/git/__init__.py
azure/devops/released/git/git_client.py
azure/devops/released/git/git_client_base.py
azure/devops/released/identity/__init__.py
azure/devops/released/identity/identity_client.py
azure/devops/released/notification/__init__.py
azure/devops/released/notification/notification_client.py
azure/devops/released/operations/__init__.py
azure/devops/released/operations/operations_client.py
azure/devops/released/policy/__init__.py
azure/devops/released/policy/policy_client.py
azure/devops/released/profile/__init__.py
azure/devops/released/profile/profile_client.py
azure/devops/released/release/__init__.py
azure/devops/released/release/release_client.py
azure/devops/released/security/__init__.py
azure/devops/released/security/security_client.py
azure/devops/released/service_hooks/__init__.py
azure/devops/released/service_hooks/service_hooks_client.py
azure/devops/released/task/__init__.py
azure/devops/released/task/task_client.py
azure/devops/released/task_agent/__init__.py
azure/devops/released/task_agent/task_agent_client.py
azure/devops/released/test/__init__.py
azure/devops/released/test/test_client.py
azure/devops/released/test_plan/__init__.py
azure_devops_v6-6.0.0.dist-info/licenses/LICENSE.txt
azure_devops_v6-6.0.0.dist-info/METADATA
azure_devops_v6-6.0.0.dist-info/WHEEL
azure_devops_v6-6.0.0.dist-info/top_level.txt
azure_devops_v6-6.0.0.dist-info/RECORD
